dipend_graph/__init__.py
dipend_graph/dipend_graph_server.py
dipend_graph/graph_data_handler.py
dipend_graph/request_handler.py
dipend_graph/public/index.html
dipend_graph/public/page.js
dipend_graph-1.0.0.dist-info/licenses/LICENSE
dipend_graph-1.0.0.dist-info/METADATA
dipend_graph-1.0.0.dist-info/WHEEL
dipend_graph-1.0.0.dist-info/top_level.txt
dipend_graph-1.0.0.dist-info/RECORD
