Metadata-Version: 2.4
Name: dipend-graph
Version: 1.0.0
Summary: A library for generating a DAG (Directed Acyclic Graph) of dependencies registered in Dipend's dependency container.
Author-email: "Saulo V. Alvarenga" <saulo.va@protonmail.com>
License-Expression: Apache-2.0
Project-URL: Homepage, https://github.com/saulova/py-dipend
Project-URL: Documentation, https://dipend.sauloalvarenga.dev.br
Project-URL: Repository, https://github.com/saulova/py-dipend
Project-URL: Issues, https://github.com/saulova/py-dipend/issues
Classifier: Intended Audience :: Developers
Classifier: Operating System :: OS Independent
Classifier: Programming Language :: Python :: 3.12
Classifier: Topic :: Software Development
Classifier: Topic :: Software Development :: Libraries
Classifier: Topic :: Software Development :: Libraries :: Application Frameworks
Classifier: Topic :: Software Development :: Libraries :: Python Modules
Classifier: Topic :: Utilities
Classifier: Typing :: Typed
Requires-Python: >=3.12
License-File: LICENSE
Dynamic: license-file
